[{"year":1950,"South America":111510265},{"year":1951,"South America":114578372},{"year":1952,"South America":117697452},{"year":1953,"South America":120896073},{"year":1954,"South America":124193500},{"year":1955,"South America":127603649},{"year":1956,"South America":131135745},{"year":1957,"South America":134777981},{"year":1958,"South America":138532601},{"year":1959,"South America":142399642},{"year":1960,"South America":146380203},{"year":1961,"South America":150421395},{"year":1962,"South America":154566314},{"year":1963,"South America":158804900},{"year":1964,"South America":163141384},{"year":1965,"South America":167579505},{"year":1966,"South America":172064574},{"year":1967,"South America":176591305},{"year":1968,"South America":181164376},{"year":1969,"South America":185793747},{"year":1970,"South America":190518252},{"year":1971,"South America":195213122},{"year":1972,"South America":199933522},{"year":1973,"South America":204711035},{"year":1974,"South America":209546686},{"year":1975,"South America":214394258},{"year":1976,"South America":219221924},{"year":1977,"South America":224200592},{"year":1978,"South America":229287250},{"year":1979,"South America":234546756},{"year":1980,"South America":239911624},{"year":1981,"South America":245338182},{"year":1982,"South America":250901106},{"year":1983,"South America":256488719},{"year":1984,"South America":262104560},{"year":1985,"South America":267701798},{"year":1986,"South America":273263637},{"year":1987,"South America":278836317},{"year":1988,"South America":284425345},{"year":1989,"South America":290024034},{"year":1990,"South America":295578202},{"year":1991,"South America":300829125},{"year":1992,"South America":306076218},{"year":1993,"South America":311360607},{"year":1994,"South America":316667969},{"year":1995,"South America":321866403},{"year":1996,"South America":326944271},{"year":1997,"South America":331984729},{"year":1998,"South America":336987371},{"year":1999,"South America":341832740},{"year":2000,"South America":346533350},{"year":2001,"South America":351236337},{"year":2002,"South America":355961327},{"year":2003,"South America":360715189},{"year":2004,"South America":365467296},{"year":2005,"South America":370117771},{"year":2006,"South America":374601914},{"year":2007,"South America":378937163},{"year":2008,"South America":383214865},{"year":2009,"South America":387423371},{"year":2010,"South America":391540857},{"year":2011,"South America":395607023},{"year":2012,"South America":399617121},{"year":2013,"South America":403571698},{"year":2014,"South America":407473286},{"year":2015,"South America":411308805},{"year":2016,"South America":415083418},{"year":2017,"South America":418802586},{"year":2018,"South America":422461086},{"year":2019,"South America":426054696},{"year":2020,"South America":429578361},{"year":2021,"South America":433032540},{"year":2022,"South America":436416777},{"year":2023,"South America":439726122},{"year":2024,"South America":442956039},{"year":2025,"South America":446102594},{"year":2026,"South America":449165817},{"year":2027,"South America":452143810},{"year":2028,"South America":455030406},{"year":2029,"South America":457820421},{"year":2030,"South America":460508725},{"year":2031,"South America":463091526},{"year":2032,"South America":465565155},{"year":2033,"South America":467925839},{"year":2034,"South America":470170724},{"year":2035,"South America":472296948},{"year":2036,"South America":474305105},{"year":2037,"South America":476195681},{"year":2038,"South America":477967179},{"year":2039,"South America":479619790},{"year":2040,"South America":481154021},{"year":2041,"South America":482571600},{"year":2042,"South America":483875063},{"year":2043,"South America":485066261},{"year":2044,"South America":486146531},{"year":2045,"South America":487117856},{"year":2046,"South America":487980852},{"year":2047,"South America":488736141},{"year":2048,"South America":489385774},{"year":2049,"South America":489931328},{"year":2050,"South America":490374695}]